{
  "arch": "x86_64",
  "build": "py37_0",
  "build_number": 0,
  "channel": "https://conda.anaconda.org/conda-forge/linux-64",
  "constrains": [],
  "depends": [
    "ipython_genutils",
    "jupyter_contrib_core >=0.3.3",
    "jupyter_core",
    "jupyter_highlight_selected_word >=0.1.1",
    "jupyter_latex_envs >=1.3.8",
    "jupyter_nbextensions_configurator >=0.4.0",
    "lxml",
    "nbconvert >=4.2",
    "notebook >=4.0",
    "python >=3.7,<3.8.0a0",
    "pyyaml",
    "tornado",
    "traitlets >=4.1"
  ],
  "features": "",
  "fn": "jupyter_contrib_nbextensions-0.5.1-py37_0.tar.bz2",
  "license": "BSD-3-Clause",
  "md5": "03a4e3ee06fecbf336521dacf847acc4",
  "name": "jupyter_contrib_nbextensions",
  "platform": "linux",
  "sha256": "e82d8c9447af27528ad974757fa465f4e9fbe0f2f032c18e5ae8a46c8ef67892",
  "size": 20363388,
  "subdir": "linux-64",
  "timestamp": 1546444180572,
  "track_features": "",
  "url": "https://conda.anaconda.org/conda-forge/linux-64/jupyter_contrib_nbextensions-0.5.1-py37_0.tar.bz2",
  "version": "0.5.1"
}